{
  "name": "Forms Node Development Container",
  "dockerComposeFile": "docker-compose.yml",
  "service": "dev",
  "workspaceFolder": "/src",
  "shutdownAction": "stopCompose",
  "features": {
    "aws-cli": {
      "version": "2.5.6"
    },
    "ghcr.io/devcontainers/features/docker-outside-of-docker:1": {}
  },
  "customizations": {
    "vscode": {
      "settings": {
        "prettier.configPath": ".prettierrc.json",
        "prettier.useEditorConfig": false
      },
      "extensions": [
        "mtxr.sqltools",
        "mtxr.sqltools-driver-pg",
        "github.copilot",
        "github.vscode-github-actions"
      ]
    }
  },
  "remoteUser": "node"
}