{
  "internalTitleEn": "Contact Us - Canada.ca",
  "internalTitleFr": "Nous joindre - Canada.ca",
  "publishingStatus": false,
  "submission": {
    "templateID": "",
    "email": "forms-formulaires@cds-snc.ca"
  },
  "form": {
    "id": 46,
    "version": 1,
    "titleEn": "Send a question or comment",
    "titleFr": "Envoyez une question ou un commentaire",
    "layout": [1, 2, 3, 4, 5, 6, 7],
    },
    "endPage": {
      "descriptionEn": "#Thank you for your email  \n\r Our delay to answer is approximately 3 days.",
      "descriptionFr": "#Merci pour votre demande  \n\r Notre délai de réponse est d'environ 4 jours.",
    },
    "elements": [
      {
        "id": 1,
        "type": "richText",
        "properties": {
          "titleEn": "Files and applications",
          "titleFr": "Dossiers et demandes",
          "descriptionEn": "###Files and applications \n\r Case specific enquiries about your file or application **must be directed** to the program at the relevant <li><a href='https://www.canada.ca/en/contact.html'>Government of Canada contacts</a></li></ul>",
          "descriptionFr": "###Dossiers et demandes \n\r Les demandes de renseignements concernant votre dossier ou votre demande doivent être adressées au programme approprié, via les <li><a href='https://www.canada.ca/fr/contact.html'>coordonnées du gouvernement du Canada</a></li></ul>",
          "charLimit": 200,
          "validation": {
            "required": false
          }
        }
      },
      {
        "id": 2,
        "type": "richText",
        "properties": {
          "titleEn": "Service hours",
          "titleFr": "Heures de service",
          "descriptionEn": "###Service hours \n\r Emails are answered from Monday to Friday, 8:00 am to 8:00 pm (Eastern Standard Time).",
          "descriptionFr": "###Heures de service \n\r Nous répondons aux courriels du lundi au vendredi, de 8 h à 20 h (heure normale de l’Est).",
          "charLimit": 200,
          "validation": {
            "required": false
          }
        }
      },
      {
        "id": 3,
        "type": "richText",
        "properties": {
          "titleEn": "Wait time",
          "titleFr": "Temps d’attente",
          "descriptionEn": "###Wait time \n\r Our delay to answer is approximately 3 days",
          "descriptionFr": "###Temps d’attente \n\r Notre délai de réponse est d'environ 4 jours.",
          "charLimit": 200,
          "validation": {
            "required": false
          }
        }
      },
      {
          "id": 4,
        "type": "richText",
        "properties": {
          "titleEn": "Personal information",
          "titleFr": "personnels de nature délicate",
          "descriptionEn": "Please do not include sensitive personal information in the questions/comments box, such as your social insurance number, personal finance data and medical or work history.",
          "descriptionFr": "Veuillez **ne pas fournir de renseignements personnels de nature délicate** dans le champ des questions/commentaires, comme votre numéro d'assurance sociale, vos données financières personnelles et vos antécédents médicaux ou professionnels. ",
          "charLimit": 200,
          "validation": {
            "required": false
          }
        }
      },
      {
       "id": 6,
        "type": "textArea",
        "properties": {
          "titleEn": "Message",
          "titleFr": "Message",
          "placeholderEn": "",
          "placeholderFr": "",
          "descriptionEn": "Your question or comment",
          "descriptionFr": "Inscrivez vos questions ou commentaires",
          "charLimit": 800,
          "validation": {
            "required": true
            "type": "Text"
          }
        }
      },
      {
        "id": 7,
        "type": "textField",
        "properties": {
          "titleEn": "Email",
          "titleFr": "Courriel",
          "placeholderEn": "",
          "placeholderFr": "",
          "descriptionEn": "",
          "descriptionFr": "",
          "charLimit": 100,
          "validation": {
            "required": true,
            "type": "email"
          }
        }
      }
    ]
  }
}
